{
	"format_version": "1.9.0",
	"credit": "Made with Blockbench",
	"texture_size": [32, 32],
	"textures": {
		"0": "dwarfcivilisation:item/tools/war_axe",
		"particle": "dwarfcivilisation:item/tools/war_axe"
	},
	"elements": [
		{
			"from": [7, 0, 8],
			"to": [9, 32, 10],
			"rotation": {"angle": 0, "axis": "y", "origin": [7, 0, 8]},
			"faces": {
				"north": {"uv": [0, 0, 1, 16], "texture": "#0"},
				"east": {"uv": [1, 0, 2, 16], "texture": "#0"},
				"south": {"uv": [2, 0, 3, 16], "texture": "#0"},
				"west": {"uv": [3, 0, 4, 16], "texture": "#0"},
				"up": {"uv": [8.5, 6, 7.5, 5], "texture": "#0"},
				"down": {"uv": [8.5, 6, 7.5, 7], "texture": "#0"}
			}
		},
		{
			"from": [7.5, 24, 10],
			"to": [8.5, 31, 17],
			"rotation": {"angle": 0, "axis": "y", "origin": [7, 24, 10]},
			"faces": {
				"north": {"uv": [10, 5, 10.5, 8.5], "texture": "#0"},
				"east": {"uv": [4, 0, 7.5, 3.5], "texture": "#0"},
				"south": {"uv": [10, 8.5, 10.5, 12], "texture": "#0"},
				"west": {"uv": [4, 3.5, 7.5, 7], "texture": "#0"},
				"up": {"uv": [4.5, 14, 4, 10.5], "texture": "#0"},
				"down": {"uv": [5, 10.5, 4.5, 14], "texture": "#0"}
			}
		},
		{
			"from": [7.51, 22.01, 12.01],
			"to": [8.49, 26.99, 16.99],
			"rotation": {"angle": -45, "axis": "x", "origin": [7, 29, 12]},
			"faces": {
				"north": {"uv": [6.5, 10.5, 7, 13], "texture": "#0"},
				"east": {"uv": [7.5, 0, 10, 2.5], "texture": "#0"},
				"south": {"uv": [7, 10.5, 7.5, 13], "texture": "#0"},
				"west": {"uv": [7.5, 2.5, 10, 5], "texture": "#0"},
				"up": {"uv": [8, 13, 7.5, 10.5], "texture": "#0"},
				"down": {"uv": [8.5, 10.5, 8, 13], "texture": "#0"}
			}
		},
		{
			"from": [7.51, 22.01, -2.99],
			"to": [8.49, 26.99, 1.99],
			"rotation": {"angle": -45, "axis": "x", "origin": [7, 29, -3]},
			"faces": {
				"north": {"uv": [8.5, 10.5, 9, 13], "texture": "#0"},
				"east": {"uv": [10, 0, 12.5, 2.5], "texture": "#0"},
				"south": {"uv": [10.5, 8.5, 11, 11], "texture": "#0"},
				"west": {"uv": [10, 2.5, 12.5, 5], "texture": "#0"},
				"up": {"uv": [9.5, 13, 9, 10.5], "texture": "#0"},
				"down": {"uv": [10, 10.5, 9.5, 13], "texture": "#0"}
			}
		},
		{
			"from": [7.5, 24, 2],
			"to": [8.5, 31, 8],
			"rotation": {"angle": 0, "axis": "y", "origin": [7, 24, 2]},
			"faces": {
				"north": {"uv": [5, 10.5, 5.5, 14], "texture": "#0"},
				"east": {"uv": [4, 7, 7, 10.5], "texture": "#0"},
				"south": {"uv": [10.5, 5, 11, 8.5], "texture": "#0"},
				"west": {"uv": [7, 7, 10, 10.5], "texture": "#0"},
				"up": {"uv": [6, 13.5, 5.5, 10.5], "texture": "#0"},
				"down": {"uv": [6.5, 10.5, 6, 13.5], "texture": "#0"}
			}
		}
	],
	"groups": [
		{
			"name": "war_axe_root",
			"origin": [8, 8, 8],
			"color": 0,
			"children": [0, 1, 2, 3, 4]
		}
	]
}